Metadata-Version: 2.1
Name: advancedcalc
Version: 0.0.3
Summary: An Advanved Calculator with Trignometry and Other Functions
Home-page: https://github.com/ProgrammerAyush7/AdvancedCalc/
Author-email: programmerayush777@gmail.com
License: MIT
Keywords: calculator
Platform: UNKNOWN
Classifier: Development Status :: 5 - Production/Stable
Classifier: Intended Audience :: Education
Classifier: Operating System :: Microsoft :: Windows :: Windows 10
Classifier: License :: OSI Approved :: MIT License
Classifier: Programming Language :: Python :: 3
